infinibatch/__init__.py
infinibatch/datasets.py
infinibatch/iterators.py
infinibatch-0.1.1.dist-info/LICENSE
infinibatch-0.1.1.dist-info/METADATA
infinibatch-0.1.1.dist-info/WHEEL
infinibatch-0.1.1.dist-info/top_level.txt
infinibatch-0.1.1.dist-info/RECORD
