Metadata-Version: 2.1
Name: infinibatch
Version: 0.1.1
Summary: Infinibatch is a library of checkpointable iterators for randomized data loading of massive data sets in deep neural network training.
Home-page: https://github.com/microsoft/infinibatch
Download-URL: https://github.com/microsoft/infinibatch
Author: Frank Seide
Author-email: fseide@microsoft.com
Keywords: datasets,NLP,natural language processing,computational linguistics
Platform: any
Requires-Python: >=3.5
License-File: LICENSE
